{
  "schema": "ts-xlsx/backlog-item@1",
  "repo": "exceljs/exceljs",
  "number": 1061,
  "type": "pull_request",
  "url": "https://github.com/exceljs/exceljs/pull/1061",
  "title": "Add ability to set fill style for a range ",
  "state": "open",
  "author": "iabukai",
  "createdAt": "2019-12-22T19:48:07Z",
  "closedAt": null,
  "labels": [],
  "reactions": 0,
  "commentCount": 7,
  "body": "",
  "comments": [
    {
      "author": "alubbe",
      "authorAssociation": "MEMBER",
      "createdAt": "2020-02-06T10:50:19Z",
      "reactions": 1,
      "body": "@iabukai just wanted to check on the status of this PR - will you be able to address @Siemienik's comments?"
    },
    {
      "author": "Siemienik",
      "authorAssociation": "MEMBER",
      "createdAt": "2020-03-31T18:06:49Z",
      "reactions": 0,
      "body": "@alubbe I've just made required changes, could you review this?"
    },
    {
      "author": "alubbe",
      "authorAssociation": "MEMBER",
      "createdAt": "2020-05-20T19:15:35Z",
      "reactions": 0,
      "body": "Please merge the current master into your branch"
    },
    {
      "author": "iabukai",
      "authorAssociation": "NONE",
      "createdAt": "2020-05-20T23:34:23Z",
      "reactions": 0,
      "body": "> \r\n> \r\n> Please merge the current master into your branch\r\n\r\n@alubbe, done! "
    },
    {
      "author": "alubbe",
      "authorAssociation": "MEMBER",
      "createdAt": "2020-05-21T06:30:10Z",
      "reactions": 0,
      "body": "Thanks @iabukai - could you take a look at the review comments that @Siemienik and I left? Should be simple to address and then we're ready to merge"
    },
    {
      "author": "iabukai",
      "authorAssociation": "NONE",
      "createdAt": "2020-05-21T10:14:52Z",
      "reactions": 0,
      "body": "> \r\n> \r\n> Thanks @iabukai - could you take a look at the review comments that @Siemienik and I left? Should be simple to address and then we're ready to merge\r\n\r\nI'll do it next week! \r\nThanks for \"pushing\" me. I was lost for a while."
    },
    {
      "author": "alubbe",
      "authorAssociation": "MEMBER",
      "createdAt": "2020-06-02T17:18:45Z",
      "reactions": 0,
      "body": "no worries, just give it a shot when you have the time. too bad that you missed the mergefest, but I'm happy to have another look once you've made the changes 👍 "
    }
  ],
  "attachments": [],
  "pr": {
    "merged": false,
    "mergeable": true,
    "baseRef": "master",
    "additions": 86,
    "deletions": 6,
    "changedFiles": [
      {
        "path": "README.md",
        "status": "modified",
        "additions": 13,
        "deletions": 0
      },
      {
        "path": "README_zh.md",
        "status": "modified",
        "additions": 12,
        "deletions": 0
      },
      {
        "path": "index.d.ts",
        "status": "modified",
        "additions": 1,
        "deletions": 1
      },
      {
        "path": "lib/doc/worksheet.js",
        "status": "modified",
        "additions": 18,
        "deletions": 1
      },
      {
        "path": "lib/utils/under-dash.js",
        "status": "modified",
        "additions": 27,
        "deletions": 1
      },
      {
        "path": "spec/integration/workbook/workbook.spec.js",
        "status": "modified",
        "additions": 15,
        "deletions": 3
      }
    ]
  }
}
