{
  "schema": "ts-xlsx/backlog-item@1",
  "repo": "exceljs/exceljs",
  "number": 1601,
  "type": "issue",
  "url": "https://github.com/exceljs/exceljs/issues/1601",
  "title": "[BUG] Uncaught TypeError: Pa.Workbook is not a constructor",
  "state": "open",
  "author": "Gabriel-Moscone",
  "createdAt": "2021-01-29T12:40:41Z",
  "closedAt": null,
  "labels": [],
  "reactions": 1,
  "commentCount": 1,
  "body": "## 🐛 Bug Report\r\n\r\nI tried to use exceljs on **React.js** to export a XLSX file, but the code are returning a error: Uncaught TypeError: Pa.Workbook is not a constructor\r\n\r\n    \"react\": \"^17.0.1\",\r\n    \"exceljs\": \"^4.2.0\",\r\n    \"file-saver\": \"^2.0.5\",\r\n\r\n## Steps To Reproduce\r\n\r\n<!-- The exact steps required to reproduce the issue, ideally with a code example -->\r\n\r\n# Imports \r\n```\r\n\r\nimport * as fs from 'file-saver';\r\nconst Excel = require('exceljs');\r\n```\r\n\r\n# Code that generates the error \r\n    let workbook = new Excel.Workbook();\r\n    const worksheet = workbook.addWorksheet(fileName);\r\n    worksheet.columns = header; \r\n    worksheet.addRows(data);\r\n\r\nThe variables come from the props \r\n\r\n# Error Message\r\n`Uncaught TypeError: Pa.Workbook is not a constructor\r\n`\r\n## The expected behaviour:\r\n\r\nCode works fine\r\n",
  "comments": [
    {
      "author": "nils-hoyer",
      "authorAssociation": "NONE",
      "createdAt": "2023-04-13T14:00:10Z",
      "reactions": 1,
      "body": "using default export worked for me. \r\n\r\n`import Excel from 'exceljs'` instead of `import * as Excel from 'exceljs'`"
    }
  ],
  "attachments": []
}
