{
  "schema": "ts-xlsx/backlog-item@1",
  "repo": "exceljs/exceljs",
  "number": 2136,
  "type": "issue",
  "url": "https://github.com/exceljs/exceljs/issues/2136",
  "title": "[BUG] Setting alignment will affect other cells",
  "state": "open",
  "author": "sagat101",
  "createdAt": "2022-09-20T02:38:40Z",
  "closedAt": null,
  "labels": [],
  "reactions": 0,
  "commentCount": 4,
  "body": "## 🐛 Bug Report\r\n\r\n<!-- A clear and concise description of what the bug is. -->\r\nSetting alignment to a cell or column will affect other cells\r\n\r\nLib version: 4.3.0\r\n\r\n## Steps To Reproduce\r\n\r\n<!-- The exact steps required to reproduce the issue, ideally with a code example -->\r\n\r\n```ExpressJS\r\nlet rotateCol = 'D'\r\nconst wb = new ExcelJS.Workbook();\r\nlet file = Buffer.from(body.excelBase64, 'base64');\r\nawait wb.xlsx.load(file);\r\n\r\n// 1. by looping each column => the result it will rotate all cell's text to 90 degress\r\nwb.eachSheet(function (worksheet, sheetId) {\r\nworksheet.columns.forEach(col => {\r\n  if (col.letter == rotateCol) {\r\n    col.style.alignment.textRotation = 90;\r\n  }\r\n})\r\n})\r\n\r\n// 2. by looping each row and getting specific cell => the result it will rotate all cell's text to 90 degress\r\nwb.eachSheet(function (worksheet, sheetId) {\r\n  worksheet.eachRow(function(row, rowNum) {\r\n      worksheet.getCell(rotateCol + rowNum).alignment.textRotation == 90;\r\n      // worksheet.getCell(rotateCol + rowNum)model.style.alignment.textRotation == 90; // doesn't work either\r\n  })\r\n})\r\n\r\n\r\n// 3. By looping rows and cells\r\nwb.eachSheet(function (worksheet, sheetId) {\r\n let rowCount = worksheet.rowCount;\r\n let columnCount = worksheet.columnCount;\r\n  for (let i = 1; i <= rowCount; i++) {\r\n     let row = worksheet.getRow(i);\r\n     for (let j = 1; j <= columnCount; j++) {\r\n        if (row._cells._address[0] == rotateCol) {\r\n           row._cells.alignment.textRotation = 90;\r\n           break; // continue to next row\r\n        }\r\n     }\r\n  }\r\n})\r\n```\r\n\r\n## The expected behaviour:\r\n\r\nThe result that I expected was only the texts of \"column D\" will rotate but the result that I got is all the texts in all columns also rotate.\r\n\r\n\r\n## Possible solution (optional, but very helpful):\r\nIt seems that the alignment is shared to cells, rows, and column.\r\n\r\nI tried debugging the 3rd attempt\r\n```javascript\r\nwb.eachSheet(function (worksheet, sheetId) {\r\n let rowCount = worksheet.rowCount;\r\n let columnCount = worksheet.columnCount;\r\n  for (let i = 1; i <= rowCount; i++) {\r\n     let row = worksheet.getRow(i);\r\n     for (let j = 1; j <= columnCount; j++) {\r\n        if (row._cells._address[0] == rotateCol) {\r\n           row._cells.alignment.textRotation = 90;               // => after this line executes, all the cells in that row will also have textRotation alignment\r\n           break; // continue to next row\r\n        }\r\n     }\r\n  }\r\n})\r\n```\r\n\r\nI hope somebody have some solution or tips.\r\nThank you very much\r\n",
  "comments": [
    {
      "author": "yunzaifei",
      "authorAssociation": "NONE",
      "createdAt": "2022-12-08T08:51:30Z",
      "reactions": 0,
      "body": "+1"
    },
    {
      "author": "HarryMath",
      "authorAssociation": "NONE",
      "createdAt": "2023-08-21T19:57:59Z",
      "reactions": 0,
      "body": "+1"
    },
    {
      "author": "reactuz",
      "authorAssociation": "NONE",
      "createdAt": "2024-01-03T12:16:07Z",
      "reactions": 0,
      "body": "+1"
    },
    {
      "author": "reactuz",
      "authorAssociation": "NONE",
      "createdAt": "2024-01-03T12:16:49Z",
      "reactions": 0,
      "body": "@sagat101 @yunzaifei @HarryMath \r\nHave you been able to find any workaround for this?"
    }
  ],
  "attachments": []
}
