{
  "schema": "ts-xlsx/backlog-item@1",
  "repo": "exceljs/exceljs",
  "number": 2554,
  "type": "issue",
  "url": "https://github.com/exceljs/exceljs/issues/2554",
  "title": "[BUG] .NET IO interop and more",
  "state": "open",
  "author": "Freymaurer",
  "createdAt": "2023-10-12T14:12:35Z",
  "closedAt": null,
  "labels": [],
  "reactions": 1,
  "commentCount": 0,
  "body": "## 🐛 Bug Report\r\n\r\nHello! We noticed quite some issues with exceljs and because of a multitude of open Pull Requests and issues we thought we just fork it and fix these issues ourselves. This is the fork in question: [fork](https://github.com/nfdi4plants/exceljs).\r\n\r\nAs this repo is seeing some activity again, we wanted to file an issue with our changes. Sadly we did not document exact cases in the first bug fixes, but they occured reading files with exceljs that were written with [OpenXML](https://github.com/dotnet/Open-XML-SDK).\r\n\r\nI updated the [README.md](https://github.com/nfdi4plants/exceljs#changes-since-fork) on our fork to reflect our fixes with the specific commit and a short description. In addition i will explain future issues more in-depth on this README.md\r\n\r\nLib version: 4.3.0\r\n\r\n## Possible solution (optional, but very helpful):\r\n\r\nThe forked branch contains the fixes we implemented to make it work. Possibly not the best solutions but any input would be welcome!\r\n\r\nFeel free to tag me here if you want to solve these issues on the main repo. I will gladly provide anything required.\r\n",
  "comments": [],
  "attachments": [
    {
      "url": "https://github.com/nfdi4plants/exceljs",
      "ext": null,
      "isFixture": false
    },
    {
      "url": "https://github.com/dotnet/Open-XML-SDK",
      "ext": null,
      "isFixture": false
    },
    {
      "url": "https://github.com/nfdi4plants/exceljs#changes-since-fork",
      "ext": null,
      "isFixture": false
    }
  ]
}
