{
  "schema": "ts-xlsx/backlog-item@1",
  "repo": "exceljs/exceljs",
  "number": 2811,
  "type": "issue",
  "url": "https://github.com/exceljs/exceljs/issues/2811",
  "title": "Export data to excel (react-native)",
  "state": "open",
  "author": "ValyaBabenkov",
  "createdAt": "2024-08-26T18:00:47Z",
  "closedAt": null,
  "labels": [],
  "reactions": 1,
  "commentCount": 0,
  "body": "Good afternoon.\r\nI am writing an application on react-native 0.74.\r\nI tried to make data upload in excel format, with attached images (pictures)\r\n\r\nBut the information on the Internet - very little.\r\nCan anyone, faced how to do it correctly.\r\n\r\nI would be grateful.\r\nThank you.",
  "comments": [],
  "attachments": []
}
